[
  {
    "id": "6948990c05f4f91bdb9a56f3",
    "imageUrl": "/files/achievement/cheatericon.png",
    "assetPath": "",
    "rewards": [
    ],
    "conditions": {
      "availableForFinish": [
        {
          "id": "69489941b354f16f009a56f6",
          "index": 0,
          "dynamicLocale": false,
          "visibilityConditions": [],
          "globalQuestCounterId": "",
          "parentId": "",
          "conditionType": "Block"
        }
      ],
      "fail": []
    },
    "instantComplete": true,
    "showNotificationsInGame": true,
    "showProgress": false,
    "prefab": "",
    "rarity": "Legendary",
    "hidden": false,
    "showConditions": false,
    "progressBarEnabled": true,
    "side": "Pmc",
    "index": 19001
  },
  {
    "id": "694d58833cff7ff7be31c5e8",
    "imageUrl": "/files/achievement/twitchguyicon.png",
    "assetPath": "",
    "rewards": [
      {
        "id": "694d5b15a2f65de51831c5ed",
        "unknown": false,
        "gameMode": [
          "regular",
          "pve"
        ],
        "availableInGameEditions": [],
        "illustrationConfig": null,
        "isHidden": false,
        "target": "694d5b11eb5884255831c5ec",
        "value": 1,
        "isEncoded": false,
        "findInRaid": true,
        "items": [
          {
            "_id": "694d5b11eb5884255831c5ec",
            "_tpl": "6937ecc3dbdccab44605fcf0",
            "upd": {
              "SpawnedInSession": true,
              "StackObjectsCount": 1
            }
          }
        ],
        "type": "Item"
      },
      {
        "id": "694d6100947c14b3c931c605",
        "unknown": false,
        "gameMode": [
          "regular",
          "pve"
        ],
        "availableInGameEditions": [],
        "illustrationConfig": null,
        "isHidden": false,
        "target": "694d61014625f4192131c606",
        "value": 1,
        "isEncoded": false,
        "findInRaid": true,
        "items": [
          {
            "_id": "694d61014625f4192131c606",
            "_tpl": "68f25b772605ccea240dd684",
            "upd": {
              "SpawnedInSession": true,
              "StackObjectsCount": 1
            }
          }
        ],
        "type": "Item"
      },
      {
        "id": "694d611570e58f10d431c608",
        "unknown": false,
        "gameMode": [
          "regular",
          "pve"
        ],
        "availableInGameEditions": [],
        "illustrationConfig": null,
        "isHidden": false,
        "target": "694d6112ebcde84a5b31c607",
        "value": 1,
        "isEncoded": false,
        "findInRaid": true,
        "items": [
          {
            "_id": "694d6112ebcde84a5b31c607",
            "_tpl": "688b2e574172ca83e70cf868",
            "upd": {
              "SpawnedInSession": true,
              "StackObjectsCount": 1
            }
          }
        ],
        "type": "Item"
      },
      {
        "id": "694d5ba7f3f792e59031c5f0",
        "unknown": false,
        "gameMode": [
          "regular",
          "pve"
        ],
        "availableInGameEditions": [],
        "illustrationConfig": null,
        "isHidden": false,
        "target": "694d5ba6ba1951091431c5ef",
        "value": 1,
        "isEncoded": false,
        "findInRaid": true,
        "items": [
          {
            "_id": "694d5ba6ba1951091431c5ef",
            "_tpl": "6937eccbfd921faceb0dfecd",
            "upd": {
              "SpawnedInSession": true,
              "StackObjectsCount": 1
            }
          }
        ],
        "type": "Item"
      },
      {
        "id": "694d5c972fd6f1d20631c5f2",
        "unknown": false,
        "gameMode": [
          "regular",
          "pve"
        ],
        "availableInGameEditions": [],
        "illustrationConfig": null,
        "isHidden": false,
        "target": "694d5c912184e8896831c5f1",
        "value": 1,
        "isEncoded": false,
        "findInRaid": true,
        "items": [
          {
            "_id": "694d5c912184e8896831c5f1",
            "_tpl": "68f117b8121d878a2303eee0",
            "upd": {
              "SpawnedInSession": true,
              "StackObjectsCount": 1
            }
          }
        ],
        "type": "Item"
      },
      {
        "id": "694d5cd8c469d9068031c5f4",
        "unknown": false,
        "gameMode": [
          "regular",
          "pve"
        ],
        "availableInGameEditions": [],
        "illustrationConfig": null,
        "isHidden": false,
        "target": "694d5cd4b5789bf0ae31c5f3",
        "value": 1,
        "isEncoded": false,
        "findInRaid": true,
        "items": [
          {
            "_id": "694d5cd4b5789bf0ae31c5f3",
            "_tpl": "68d55968ca9935b3f10607a9",
            "upd": {
              "SpawnedInSession": true,
              "StackObjectsCount": 1
            }
          }
        ],
        "type": "Item"
      },
      {
        "id": "694610dbd6d2fd27a09f67d8",
        "unknown": false,
        "gameMode": [],
        "availableInGameEditions": [],
        "illustrationConfig": null,
        "isHidden": false,
        "target": "68f151258e0bff44ce023f20",
        "type": "CustomizationDirect"
      },
      {
        "id": "69488ddc97118b09d89a56b2",
        "unknown": false,
        "gameMode": [],
        "availableInGameEditions": [],
        "illustrationConfig": null,
        "isHidden": false,
        "target": "68f1500a8e0bff44ce023f1e",
        "type": "CustomizationDirect"
      },
      {
        "id": "69485d43ef6d69b8f2ff89c2",
        "unknown": false,
        "gameMode": [],
        "availableInGameEditions": [],
        "illustrationConfig": null,
        "isHidden": false,
        "target": "68f151bf79e73568c40a7938",
        "type": "CustomizationDirect"
      },
      {
        "id": "6946162669e6b2b4179f67db",
        "unknown": false,
        "gameMode": [],
        "availableInGameEditions": [],
        "illustrationConfig": null,
        "isHidden": false,
        "target": "68f615b0c7592f88510b1c32",
        "type": "CustomizationDirect"
      }
    ],
    "conditions": {
      "availableForFinish": [
        {
          "id": "694d58847e7cba6bee31c5e9",
          "index": 0,
          "dynamicLocale": false,
          "visibilityConditions": [],
          "globalQuestCounterId": "",
          "parentId": "",
          "conditionType": "Block"
        }
      ],
      "fail": []
    },
    "instantComplete": true,
    "showNotificationsInGame": true,
    "showProgress": false,
    "prefab": "",
    "rarity": "Legendary",
    "hidden": false,
    "showConditions": false,
    "progressBarEnabled": true,
    "side": "Pmc",
    "index": 19001
  },
  {
    "id": "694c6575af08f6f1d59a5737",
    "imageUrl": "/files/achievement/67prestigeicon.png",
    "assetPath": "",
    "rewards": [
      {
        "id": "694d5980ab4d07aa7d31c5eb",
        "unknown": false,
        "gameMode": [
          "regular",
          "pve"
        ],
        "availableInGameEditions": [],
        "illustrationConfig": null,
        "isHidden": false,
        "target": "694d59798a66b0d06931c5ea",
        "value": 1,
        "isEncoded": false,
        "findInRaid": true,
        "items": [
          {
            "_id": "694d59798a66b0d06931c5ea",
            "_tpl": "68f117b8121d878a2303eee0",
            "upd": {
              "SpawnedInSession": true,
              "StackObjectsCount": 1
            }
          }
        ],
        "type": "Item"
      },
      {
        "id": "694d60de2e88f58b1831c603",
        "unknown": false,
        "gameMode": [
          "regular",
          "pve"
        ],
        "availableInGameEditions": [],
        "illustrationConfig": null,
        "isHidden": false,
        "target": "694d60dff38773492631c604",
        "value": 1,
        "isEncoded": false,
        "findInRaid": true,
        "items": [
          {
            "_id": "694d60dff38773492631c604",
            "_tpl": "68d65766916a108d7a023c98",
            "upd": {
              "SpawnedInSession": true,
              "StackObjectsCount": 1
            }
          }
        ],
        "type": "Item"
      },
      {
        "id": "694c65b195af104d3a9a573a",
        "unknown": false,
        "gameMode": [],
        "availableInGameEditions": [],
        "illustrationConfig": null,
        "isHidden": false,
        "target": "68f11478a1e799f1c3027c77",
        "type": "CustomizationDirect"
      },
      {
        "id": "694c65dac559349f2a9a573b",
        "unknown": false,
        "gameMode": [],
        "availableInGameEditions": [],
        "illustrationConfig": null,
        "isHidden": false,
        "target": "68f113af8c147e61f50fb520",
        "type": "CustomizationDirect"
      },
      {
        "id": "694c660033c463aac19a573d",
        "unknown": false,
        "gameMode": [],
        "availableInGameEditions": [],
        "illustrationConfig": null,
        "isHidden": false,
        "target": "68f11506a1e799f1c3027c79",
        "type": "CustomizationDirect"
      }
    ],
    "conditions": {
      "availableForFinish": [
        {
          "id": "694c6576b6d04345709a5738",
          "index": 0,
          "dynamicLocale": false,
          "visibilityConditions": [],
          "globalQuestCounterId": "",
          "parentId": "",
          "conditionType": "Block"
        }
      ],
      "fail": []
    },
    "instantComplete": true,
    "showNotificationsInGame": true,
    "showProgress": false,
    "prefab": "",
    "rarity": "Legendary",
    "hidden": false,
    "showConditions": false,
    "progressBarEnabled": true,
    "side": "Pmc",
    "index": 19001
  },
  {
    "id": "694c60b50cb1e6ad639a5723",
    "imageUrl": "/files/achievement/endingsicon.png",
    "assetPath": "",
    "rewards": [
      {
        "id": "694c61348c72377a809a5725",
        "unknown": false,
        "gameMode": [],
        "availableInGameEditions": [],
        "illustrationConfig": null,
        "isHidden": false,
        "target": "68df9aa45d4e135b130392d0",
        "type": "CustomizationDirect"
      },
      {
        "id": "694c61a990bd6024059a5736",
        "unknown": false,
        "gameMode": [],
        "availableInGameEditions": [],
        "illustrationConfig": null,
        "isHidden": false,
        "target": "68df9aaf637781242a0b22fa",
        "type": "CustomizationDirect"
      },
      {
        "id": "694c61a762f85604389a5735",
        "unknown": false,
        "gameMode": [],
        "availableInGameEditions": [],
        "illustrationConfig": null,
        "isHidden": false,
        "target": "68df9a2d3772634bf40f4f1a",
        "type": "CustomizationDirect"
      },
      {
        "id": "694c61a4a70d1244b89a5734",
        "unknown": false,
        "gameMode": [],
        "availableInGameEditions": [],
        "illustrationConfig": null,
        "isHidden": false,
        "target": "68df9ac5a38a5e37d80df6cd",
        "type": "CustomizationDirect"
      },
      {
        "id": "694c61a04b639d5f499a5733",
        "unknown": false,
        "gameMode": [],
        "availableInGameEditions": [],
        "illustrationConfig": null,
        "isHidden": false,
        "target": "68df9a14972cf1e1ec07256c",
        "type": "CustomizationDirect"
      },
      {
        "id": "694c619f8ecec149e99a5732",
        "unknown": false,
        "gameMode": [],
        "availableInGameEditions": [],
        "illustrationConfig": null,
        "isHidden": false,
        "target": "68df9abc5d4e135b130392d2",
        "type": "CustomizationDirect"
      },
      {
        "id": "694c619d728467dfe79a5731",
        "unknown": false,
        "gameMode": [],
        "availableInGameEditions": [],
        "illustrationConfig": null,
        "isHidden": false,
        "target": "68df9a925d4e135b130392ce",
        "type": "CustomizationDirect"
      },
      {
        "id": "694c619be56bf8520b9a5730",
        "unknown": false,
        "gameMode": [],
        "availableInGameEditions": [],
        "illustrationConfig": null,
        "isHidden": false,
        "target": "68df9a053772634bf40f4f18",
        "type": "CustomizationDirect"
      },
      {
        "id": "694c619ae1ea9a49b09a572f",
        "unknown": false,
        "gameMode": [],
        "availableInGameEditions": [],
        "illustrationConfig": null,
        "isHidden": false,
        "target": "68df9b2642e96f583d042b8c",
        "type": "CustomizationDirect"
      },
      {
        "id": "694c61985d10f252a19a572e",
        "unknown": false,
        "gameMode": [],
        "availableInGameEditions": [],
        "illustrationConfig": null,
        "isHidden": false,
        "target": "68df9b2e3772634bf40f4f1c",
        "type": "CustomizationDirect"
      },
      {
        "id": "694c61972021e1957c9a572d",
        "unknown": false,
        "gameMode": [],
        "availableInGameEditions": [],
        "illustrationConfig": null,
        "isHidden": false,
        "target": "68df9a9ba38a5e37d80df6cb",
        "type": "CustomizationDirect"
      },
      {
        "id": "694c61951a431fc1e09a572c",
        "unknown": false,
        "gameMode": [],
        "availableInGameEditions": [],
        "illustrationConfig": null,
        "isHidden": false,
        "target": "68df9a222e6cd294e908d1eb",
        "type": "CustomizationDirect"
      },
      {
        "id": "694c6194dfd15d4dac9a572b",
        "unknown": false,
        "gameMode": [],
        "availableInGameEditions": [],
        "illustrationConfig": null,
        "isHidden": false,
        "target": "68dfb00742e96f583d042bd2",
        "type": "CustomizationDirect"
      },
      {
        "id": "694c6192aac53715f19a572a",
        "unknown": false,
        "gameMode": [],
        "availableInGameEditions": [],
        "illustrationConfig": null,
        "isHidden": false,
        "target": "68dfafeadfaadbd4eb06539a",
        "type": "CustomizationDirect"
      },
      {
        "id": "694c61910bf702c6da9a5729",
        "unknown": false,
        "gameMode": [],
        "availableInGameEditions": [],
        "illustrationConfig": null,
        "isHidden": false,
        "target": "68dfaffe3c5a40e30f0e55b0",
        "type": "CustomizationDirect"
      },
      {
        "id": "694c6190d8fcb734bc9a5728",
        "unknown": false,
        "gameMode": [],
        "availableInGameEditions": [],
        "illustrationConfig": null,
        "isHidden": false,
        "target": "68dfafd82d57066c0d011c86",
        "type": "CustomizationDirect"
      }
    ],
    "conditions": {
      "availableForFinish": [
        {
          "id": "694c60b76becc7f81b9a5724",
          "index": 0,
          "dynamicLocale": false,
          "visibilityConditions": [],
          "globalQuestCounterId": "",
          "parentId": "",
          "conditionType": "Block"
        }
      ],
      "fail": []
    },
    "instantComplete": true,
    "showNotificationsInGame": true,
    "showProgress": false,
    "prefab": "",
    "rarity": "Legendary",
    "hidden": false,
    "showConditions": false,
    "progressBarEnabled": true,
    "side": "Pmc",
    "index": 19001
  },
  {
    "id": "694c5cae0256a6bd999a5721",
    "imageUrl": "/files/achievement/alltheclothes.png",
    "assetPath": "",
    "rewards": [
    ],
    "conditions": {
      "availableForFinish": [
        {
          "id": "694c5caf9730f8cd419a5722",
          "index": 0,
          "dynamicLocale": false,
          "visibilityConditions": [],
          "globalQuestCounterId": "",
          "parentId": "",
          "conditionType": "Block"
        }
      ],
      "fail": []
    },
    "instantComplete": true,
    "showNotificationsInGame": true,
    "showProgress": false,
    "prefab": "",
    "rarity": "Legendary",
    "hidden": false,
    "showConditions": false,
    "progressBarEnabled": true,
    "side": "Pmc",
    "index": 19001
  },
  {
    "id": "694c5527d1d40bd7db9a571a",
    "imageUrl": "/files/achievement/backstabbericon.png",
    "assetPath": "",
    "rewards": [
    ],
    "conditions": {
      "availableForFinish": [
        {
          "id": "694c552c13698940f09a571c",
          "index": 0,
          "dynamicLocale": false,
          "visibilityConditions": [],
          "globalQuestCounterId": "",
          "parentId": "",
          "conditionType": "Block"
        }
      ],
      "fail": []
    },
    "instantComplete": true,
    "showNotificationsInGame": true,
    "showProgress": false,
    "prefab": "",
    "rarity": "Legendary",
    "hidden": false,
    "showConditions": false,
    "progressBarEnabled": true,
    "side": "Pmc",
    "index": 19001
  },
  {
    "id": "6948996f192a4d4fc09a56f7",
    "imageUrl": "/files/achievement/preordericon.png",
    "assetPath": "",
    "rewards": [
      {
        "id": "694d6034e1a29377ae31c600",
        "unknown": false,
        "gameMode": [
          "regular",
          "pve"
        ],
        "availableInGameEditions": [],
        "illustrationConfig": null,
        "isHidden": false,
        "target": "694d60308c8be1e26431c5ff",
        "value": 1,
        "isEncoded": false,
        "findInRaid": true,
        "items": [
          {
            "_id": "694d60308c8be1e26431c5ff",
            "_tpl": "68f8e04eae031982b00e7aaf",
            "upd": {
              "SpawnedInSession": true,
              "StackObjectsCount": 1
            }
          }
        ],
        "type": "Item"
      },
      {
        "id": "694d602e27e2d9085a31c5fe",
        "unknown": false,
        "gameMode": [
          "regular",
          "pve"
        ],
        "availableInGameEditions": [],
        "illustrationConfig": null,
        "isHidden": false,
        "target": "694d602a946b0452c231c5fd",
        "value": 1,
        "isEncoded": false,
        "findInRaid": true,
        "items": [
          {
            "_id": "694d602a946b0452c231c5fd",
            "_tpl": "68f8ccbc4c78615ba6079b20",
            "upd": {
              "SpawnedInSession": true,
              "StackObjectsCount": 1
            }
          }
        ],
        "type": "Item"
      },
      {
        "id": "694d60258709966a3031c5fc",
        "unknown": false,
        "gameMode": [
          "regular",
          "pve"
        ],
        "availableInGameEditions": [],
        "illustrationConfig": null,
        "isHidden": false,
        "target": "694d602121c3bf281131c5fb",
        "value": 1,
        "isEncoded": false,
        "findInRaid": true,
        "items": [
          {
            "_id": "694d602121c3bf281131c5fb",
            "_tpl": "68f25be683ec644ebf046787",
            "upd": {
              "SpawnedInSession": true,
              "StackObjectsCount": 1
            }
          }
        ],
        "type": "Item"
      },
      {
        "id": "694d601f3bca407e9431c5fa",
        "unknown": false,
        "gameMode": [
          "regular",
          "pve"
        ],
        "availableInGameEditions": [],
        "illustrationConfig": null,
        "isHidden": false,
        "target": "694d601bd1f081e1e531c5f9",
        "value": 1,
        "isEncoded": false,
        "findInRaid": true,
        "items": [
          {
            "_id": "694d601bd1f081e1e531c5f9",
            "_tpl": "68f8ccb11cc53ada67036e27",
            "upd": {
              "SpawnedInSession": true,
              "StackObjectsCount": 1
            }
          }
        ],
        "type": "Item"
      },
      {
        "id": "694d60192250a0e12731c5f8",
        "unknown": false,
        "gameMode": [
          "regular",
          "pve"
        ],
        "availableInGameEditions": [],
        "illustrationConfig": null,
        "isHidden": false,
        "target": "694d601624fcecdddc31c5f7",
        "value": 1,
        "isEncoded": false,
        "findInRaid": true,
        "items": [
          {
            "_id": "694d601624fcecdddc31c5f7",
            "_tpl": "68f8ccf06a6869fe97026c3b",
            "upd": {
              "SpawnedInSession": true,
              "StackObjectsCount": 1
            }
          }
        ],
        "type": "Item"
      },
      {
        "id": "694d60b034fb9c860731c602",
        "unknown": false,
        "gameMode": [
          "regular",
          "pve"
        ],
        "availableInGameEditions": [],
        "illustrationConfig": null,
        "isHidden": false,
        "target": "694d60ac37f204c81a31c601",
        "value": 1,
        "isEncoded": false,
        "findInRaid": true,
        "items": [
          {
            "_id": "694d60ac37f204c81a31c601",
            "_tpl": "68fb9480e6ad35a767066feb",
            "upd": {
              "SpawnedInSession": true,
              "StackObjectsCount": 1
            }
          }
        ],
        "type": "Item"
      },
      {
        "id": "69489970d58abfecad9a56f8",
        "unknown": true,
        "gameMode": [],
        "availableInGameEditions": [],
        "illustrationConfig": null,
        "isHidden": false,
        "target": "68f15ed4edf2ab313f093498",
        "type": "CustomizationDirect"
      },
      {
        "id": "694b4bc36fe5b9ddf49a5710",
        "unknown": true,
        "gameMode": [],
        "availableInGameEditions": [],
        "illustrationConfig": null,
        "isHidden": false,
        "target": "68fb35fb2cff66eb7a008ea8",
        "type": "CustomizationDirect"
      },
      {
        "id": "694b4bc24b58f308449a570f",
        "unknown": true,
        "gameMode": [],
        "availableInGameEditions": [],
        "illustrationConfig": null,
        "isHidden": false,
        "target": "68fb36c5f91674307c06674d",
        "type": "CustomizationDirect"
      },
      {
        "id": "694b4bc0d84d5698f79a570e",
        "unknown": true,
        "gameMode": [],
        "availableInGameEditions": [],
        "illustrationConfig": null,
        "isHidden": false,
        "target": "68fb36ac1494ff5562048865",
        "type": "CustomizationDirect"
      },
      {
        "id": "694b4bbf4f31b146129a570d",
        "unknown": true,
        "gameMode": [],
        "availableInGameEditions": [],
        "illustrationConfig": null,
        "isHidden": false,
        "target": "68fb36dbd34d546909014ca7",
        "type": "CustomizationDirect"
      },
      {
        "id": "694b4bbc5b82a0e3629a570c",
        "unknown": true,
        "gameMode": [],
        "availableInGameEditions": [],
        "illustrationConfig": null,
        "isHidden": false,
        "target": "68fb6a28f0b98c76ea0dc313",
        "type": "CustomizationDirect"
      },
      {
        "id": "694b4bbbba56521bdb9a570b",
        "unknown": true,
        "gameMode": [],
        "availableInGameEditions": [],
        "illustrationConfig": null,
        "isHidden": false,
        "target": "68f6159355deae75be0f3bb6",
        "type": "CustomizationDirect"
      },
      {
        "id": "694b4bb9505b2b055c9a570a",
        "unknown": true,
        "gameMode": [],
        "availableInGameEditions": [],
        "illustrationConfig": null,
        "isHidden": false,
        "target": "68fb6a7cf91c87952f0c4fe5",
        "type": "CustomizationDirect"
      },
      {
        "id": "694b4bb7ed011ff84b9a5709",
        "unknown": true,
        "gameMode": [],
        "availableInGameEditions": [],
        "illustrationConfig": null,
        "isHidden": false,
        "target": "68fb6aa63545a39de907326f",
        "type": "CustomizationDirect"
      },
      {
        "id": "694b4bb6a4a6d9e0ca9a5708",
        "unknown": true,
        "gameMode": [],
        "availableInGameEditions": [],
        "illustrationConfig": null,
        "isHidden": false,
        "target": "68fb6abe365db7fe8a0e25ef",
        "type": "CustomizationDirect"
      },
      {
        "id": "694b4bb5c6681c0e279a5707",
        "unknown": true,
        "gameMode": [],
        "availableInGameEditions": [],
        "illustrationConfig": null,
        "isHidden": false,
        "target": "68fb6a703545a39de9073267",
        "type": "CustomizationDirect"
      },
      {
        "id": "694b4bb37d36d05af99a5706",
        "unknown": true,
        "gameMode": [],
        "availableInGameEditions": [],
        "illustrationConfig": null,
        "isHidden": false,
        "target": "68fb6a584e7ecdb1220adfa5",
        "type": "CustomizationDirect"
      }
    ],
    "conditions": {
      "availableForFinish": [
        {
          "id": "6948997708a71bf90b9a56f9",
          "index": 0,
          "dynamicLocale": false,
          "visibilityConditions": [],
          "globalQuestCounterId": "",
          "parentId": "",
          "conditionType": "Block"
        }
      ],
      "fail": []
    },
    "instantComplete": true,
    "showNotificationsInGame": true,
    "showProgress": false,
    "prefab": "",
    "rarity": "Legendary",
    "hidden": false,
    "showConditions": false,
    "progressBarEnabled": true,
    "side": "Pmc",
    "index": 19001
  },
  {
    "id": "6945add7f611786d999f67c9",
    "imageUrl": "/files/achievement/tagillatargeticon.png",
    "assetPath": "",
    "rewards": [
      {
        "id": "694610dbd6d2fd27a09f67d8",
        "unknown": false,
        "gameMode": [],
        "availableInGameEditions": [],
        "illustrationConfig": null,
        "isHidden": false,
        "target": "68f151258e0bff44ce023f20",
        "type": "CustomizationDirect"
      }
    ],
    "conditions": {
      "availableForFinish": [
        {
          "id": "6945addcb379c68aba9f67ca",
          "index": 0,
          "dynamicLocale": false,
          "visibilityConditions": [],
          "globalQuestCounterId": "",
          "parentId": "",
          "value": 5,
          "type": "Elimination",
          "oneSessionOnly": false,
          "completeInSeconds": 0,
          "doNotResetIfCounterCompleted": false,
          "isResetOnConditionFailed": false,
          "isNecessary": false,
          "counter": {
            "id": "6945addf1bd78a6f589f67cb",
            "conditions": [
              {
                "id": "6945ade4bf4bc996a19f67cc",
                "dynamicLocale": false,
                "target": "Savage",
                "value": 1,
                "compareMethod": ">=",
                "conditionType": "Kills",
                "weapon": [
                ],
                "bodyPart": [
                  "Head"
                ],
                "daytime": {
                  "from": 0,
                  "to": 0
                },
                "distance": {
                  "compareMethod": ">=",
                  "value": 0
                },
                "resetOnSessionEnd": false,
                "savageRole": [
                  "bossTagilla"
                ],
                "enemyEquipmentExclusive": [],
                "enemyEquipmentInclusive": [],
                "enemyHealthEffects": [],
                "weaponCaliber": [],
                "weaponModsExclusive": [],
                "weaponModsInclusive": []
              }
            ]
          },
          "conditionType": "CounterCreator"
        }
      ],
      "fail": []
    },
    "instantComplete": false,
    "showNotificationsInGame": false,
    "showProgress": false,
    "prefab": "",
    "rarity": "Rare",
    "hidden": false,
    "showConditions": false,
    "progressBarEnabled": true,
    "side": "Pmc",
    "index": 9001
  },
  {
    "id": "6948bed64eec012e689a56ff",
    "imageUrl": "/files/achievement/meltedicon.png",
    "assetPath": "",
    "rewards": [
      {
        "id": "6948bed71350e2ef8a9a5700",
        "unknown": false,
        "gameMode": [],
        "availableInGameEditions": [],
        "illustrationConfig": null,
        "isHidden": false,
        "target": "68f15ed4edf2ab313f093498",
        "type": "CustomizationDirect"
      }
    ],
    "conditions": {
      "availableForFinish": [
        {
          "id": "6948bed970e509e0fc9a5701",
          "index": 0,
          "dynamicLocale": false,
          "visibilityConditions": [],
          "globalQuestCounterId": "",
          "parentId": "",
          "value": 8,
          "type": "Elimination",
          "oneSessionOnly": true,
          "completeInSeconds": 0,
          "doNotResetIfCounterCompleted": false,
          "isResetOnConditionFailed": false,
          "isNecessary": false,
          "counter": {
            "id": "6948bedb7fc11239329a5702",
            "conditions": [
              {
                "id": "6948bede50ae278aff9a5703",
                "dynamicLocale": false,
                "target": "AnyPmc",
                "value": 1,
                "compareMethod": ">=",
                "conditionType": "Kills",
                "weapon": [
                  "5a2a57cfc4a2826c6e06d44a",
                  "5a0c27731526d80618476ac4",
                  "58d3db5386f77426186285a0",
                  "5e340dcdcb6d5863cc5e5efb",
                  "5e32f56fcb6d5863cc5e5ee4",
                  "5448be9a4bdc2dfd2f8b456a",
                  "5710c24ad2720bc3458b45a3",
                  "618a431df1eb8e24b8741deb",
                  "617fd91e5539a84ec44ce155",
                  "639c3fbbd0446708ee622ee9",
                  "639af924d0446708ee62294e",
                  "5648b62b4bdc2d9d488b4585",
                  "66dae7cbeb28f0f96809f325",
                  "67b49e7335dec48e3e05e057"
                ],
                "bodyPart": [
                ],
                "daytime": {
                  "from": 0,
                  "to": 0
                },
                "distance": {
                  "compareMethod": ">=",
                  "value": 0
                },
                "resetOnSessionEnd": false,
                "savageRole": [
                ],
                "enemyEquipmentExclusive": [],
                "enemyEquipmentInclusive": [],
                "enemyHealthEffects": [],
                "weaponCaliber": [],
                "weaponModsExclusive": [],
                "weaponModsInclusive": []
              }
            ]
          },
          "conditionType": "CounterCreator"
        }
      ],
      "fail": []
    },
    "instantComplete": false,
    "showNotificationsInGame": false,
    "showProgress": false,
    "prefab": "",
    "rarity": "Rare",
    "hidden": false,
    "showConditions": false,
    "progressBarEnabled": true,
    "side": "Pmc",
    "index": 9001
  },
  {
    "id": "6948bdfa8c37d412919a56fa",
    "imageUrl": "/files/achievement/squareicon.png",
    "assetPath": "",
    "rewards": [
      {
        "id": "6948bdfc052f9346129a56fb",
        "unknown": false,
        "gameMode": [],
        "availableInGameEditions": [],
        "illustrationConfig": null,
        "isHidden": false,
        "target": "68f15e9fcacd763bbc0e2bd8",
        "type": "CustomizationDirect"
      }
    ],
    "conditions": {
      "availableForFinish": [
        {
          "id": "6948bdfed6dac981ee9a56fc",
          "index": 0,
          "dynamicLocale": false,
          "visibilityConditions": [],
          "globalQuestCounterId": "",
          "parentId": "",
          "value": 20,
          "type": "Elimination",
          "oneSessionOnly": true,
          "completeInSeconds": 0,
          "doNotResetIfCounterCompleted": false,
          "isResetOnConditionFailed": false,
          "isNecessary": false,
          "counter": {
            "id": "6948be0160dd4a00d19a56fd",
            "conditions": [
              {
                "id": "6948be0251374461e39a56fe",
                "dynamicLocale": false,
                "target": "Any",
                "value": 1,
                "compareMethod": ">=",
                "conditionType": "Kills",
                "weapon": [
                ],
                "bodyPart": [
                ],
                "daytime": {
                  "from": 0,
                  "to": 0
                },
                "distance": {
                  "compareMethod": ">=",
                  "value": 0
                },
                "resetOnSessionEnd": false,
                "savageRole": [
                ],
                "enemyEquipmentExclusive": [],
                "enemyEquipmentInclusive": [],
                "enemyHealthEffects": [],
                "weaponCaliber": [],
                "weaponModsExclusive": [],
                "weaponModsInclusive": []
              },
              {
                "id": "694a0064a9058e9fd89a5704",
                "dynamicLocale": false,
                "target": [
                  "factory4_day",
                  "factory4_night"
                ],
                "conditionType": "Location"
              }
            ]
          },
          "conditionType": "CounterCreator"
        }
      ],
      "fail": []
    },
    "instantComplete": false,
    "showNotificationsInGame": false,
    "showProgress": false,
    "prefab": "",
    "rarity": "Rare",
    "hidden": false,
    "showConditions": false,
    "progressBarEnabled": true,
    "side": "Pmc",
    "index": 9001
  },
  {
    "id": "69488f0bc7b96c28559a56b6",
    "imageUrl": "/files/achievement/forgottenicon.png",
    "assetPath": "",
    "rewards": [
      {
        "id": "694896aa1186460d289a56f0",
        "unknown": false,
        "gameMode": [],
        "availableInGameEditions": [],
        "illustrationConfig": null,
        "isHidden": false,
        "target": "68fb6a28f0b98c76ea0dc313",
        "type": "CustomizationDirect"
      },
      {
        "id": "694896cb24aa4c27a69a56f1",
        "unknown": false,
        "gameMode": [],
        "availableInGameEditions": [],
        "illustrationConfig": null,
        "isHidden": false,
        "target": "68fb6aa63545a39de907326f",
        "type": "CustomizationDirect"
      },
      {
        "id": "694896e37d6411a8e69a56f2",
        "unknown": false,
        "gameMode": [],
        "availableInGameEditions": [],
        "illustrationConfig": null,
        "isHidden": false,
        "target": "68fb6a703545a39de9073267",
        "type": "CustomizationDirect"
      }
    ],
    "conditions": {
      "availableForFinish": [
        {
          "id": "69488f1a0d42b9def39a56b8",
          "index": 0,
          "dynamicLocale": false,
          "visibilityConditions": [],
          "globalQuestCounterId": "",
          "parentId": "",
          "value": 150,
          "type": "Elimination",
          "oneSessionOnly": false,
          "completeInSeconds": 0,
          "doNotResetIfCounterCompleted": false,
          "isResetOnConditionFailed": false,
          "isNecessary": false,
          "counter": {
            "id": "69488f1c3364e239ee9a56b9",
            "conditions": [
              {
                "id": "69488f1dc1c488be259a56ba",
                "dynamicLocale": false,
                "target": "Savage",
                "value": 1,
                "compareMethod": ">=",
                "conditionType": "Kills",
                "weapon": [
                ],
                "bodyPart": [
                  "Head"
                ],
                "daytime": {
                  "from": 0,
                  "to": 0
                },
                "distance": {
                  "compareMethod": ">=",
                  "value": 0
                },
                "resetOnSessionEnd": false,
                "savageRole": [
                  "assault",
                  "marksman"
                ],
                "enemyEquipmentExclusive": [],
                "enemyEquipmentInclusive": [],
                "enemyHealthEffects": [],
                "weaponCaliber": [],
                "weaponModsExclusive": [],
                "weaponModsInclusive": []
              }
            ]
          },
          "conditionType": "CounterCreator"
        }
      ],
      "fail": []
    },
    "instantComplete": false,
    "showNotificationsInGame": false,
    "showProgress": false,
    "prefab": "",
    "rarity": "Rare",
    "hidden": false,
    "showConditions": false,
    "progressBarEnabled": true,
    "side": "Pmc",
    "index": 9001
  },
  {
    "id": "694890e956549526659a56bb",
    "imageUrl": "/files/achievement/echoofbattleicon.png",
    "assetPath": "",
    "rewards": [
      {
        "id": "694890ea8d1a58bfdc9a56bc",
        "unknown": false,
        "gameMode": [],
        "availableInGameEditions": [],
        "illustrationConfig": null,
        "isHidden": false,
        "target": "68fb6abe365db7fe8a0e25ef",
        "type": "CustomizationDirect"
      },
      {
        "id": "6948965b4b91fa702c9a56ed",
        "unknown": false,
        "gameMode": [],
        "availableInGameEditions": [],
        "illustrationConfig": null,
        "isHidden": false,
        "target": "68fb6a584e7ecdb1220adfa5",
        "type": "CustomizationDirect"
      },
      {
        "id": "6948968e5a3d7f850a9a56ef",
        "unknown": false,
        "gameMode": [],
        "availableInGameEditions": [],
        "illustrationConfig": null,
        "isHidden": false,
        "target": "68fb6a7cf91c87952f0c4fe5",
        "type": "CustomizationDirect"
      }
    ],
    "conditions": {
      "availableForFinish": [
        {
          "id": "694890ede770941a029a56bd",
          "index": 0,
          "dynamicLocale": false,
          "visibilityConditions": [],
          "globalQuestCounterId": "",
          "parentId": "",
          "value": 10,
          "type": "Elimination",
          "oneSessionOnly": false,
          "completeInSeconds": 0,
          "doNotResetIfCounterCompleted": false,
          "isResetOnConditionFailed": false,
          "isNecessary": false,
          "counter": {
            "id": "694890efd35a1b2e249a56be",
            "conditions": [
              {
                "id": "694890f059acb81fa09a56bf",
                "dynamicLocale": false,
                "target": "AnyPmc",
                "value": 1,
                "compareMethod": ">=",
                "conditionType": "Kills",
                "weapon": [
                ],
                "bodyPart": [
                  "Head"
                ],
                "daytime": {
                  "from": 0,
                  "to": 0
                },
                "distance": {
                  "compareMethod": ">=",
                  "value": 0
                },
                "resetOnSessionEnd": false,
                "savageRole": [
                ],
                "enemyEquipmentExclusive": [],
                "enemyEquipmentInclusive": [],
                "enemyHealthEffects": [],
                "weaponCaliber": [],
                "weaponModsExclusive": [],
                "weaponModsInclusive": []
              },
              {
                "id": "694891c1adc8897ad99a56c0",
                "dynamicLocale": false,
                "target": [
                  "bigmap"
                ],
                "conditionType": "Location"
              }
            ]
          },
          "conditionType": "CounterCreator"
        },
        {
          "id": "6948920a020ecb29589a56c4",
          "index": 1,
          "dynamicLocale": false,
          "visibilityConditions": [],
          "globalQuestCounterId": "",
          "parentId": "",
          "value": 10,
          "type": "Elimination",
          "oneSessionOnly": false,
          "completeInSeconds": 0,
          "doNotResetIfCounterCompleted": false,
          "isResetOnConditionFailed": false,
          "isNecessary": false,
          "counter": {
            "id": "6948920874d00849979a56c3",
            "conditions": [
              {
                "id": "69489207a470dd14919a56c2",
                "dynamicLocale": false,
                "target": "AnyPmc",
                "value": 1,
                "compareMethod": ">=",
                "conditionType": "Kills",
                "weapon": [
                ],
                "bodyPart": [
                  "Head"
                ],
                "daytime": {
                  "from": 0,
                  "to": 0
                },
                "distance": {
                  "compareMethod": ">=",
                  "value": 0
                },
                "resetOnSessionEnd": false,
                "savageRole": [
                ],
                "enemyEquipmentExclusive": [],
                "enemyEquipmentInclusive": [],
                "enemyHealthEffects": [],
                "weaponCaliber": [],
                "weaponModsExclusive": [],
                "weaponModsInclusive": []
              },
              {
                "id": "6948920e1d322a73969a56c5",
                "dynamicLocale": false,
                "target": [
                  "factory4_day",
                  "factory4_night"
                ],
                "conditionType": "Location"
              }
            ]
          },
          "conditionType": "CounterCreator"
        },
        {
          "id": "6948922b2168533b8b9a56c9",
          "index": 2,
          "dynamicLocale": false,
          "visibilityConditions": [],
          "globalQuestCounterId": "",
          "parentId": "",
          "value": 10,
          "type": "Elimination",
          "oneSessionOnly": false,
          "completeInSeconds": 0,
          "doNotResetIfCounterCompleted": false,
          "isResetOnConditionFailed": false,
          "isNecessary": false,
          "counter": {
            "id": "6948922af3fae63c179a56c8",
            "conditions": [
              {
                "id": "69489229fef6831f299a56c7",
                "dynamicLocale": false,
                "target": "AnyPmc",
                "value": 1,
                "compareMethod": ">=",
                "conditionType": "Kills",
                "weapon": [
                ],
                "bodyPart": [
                  "Head"
                ],
                "daytime": {
                  "from": 0,
                  "to": 0
                },
                "distance": {
                  "compareMethod": ">=",
                  "value": 0
                },
                "resetOnSessionEnd": false,
                "savageRole": [
                ],
                "enemyEquipmentExclusive": [],
                "enemyEquipmentInclusive": [],
                "enemyHealthEffects": [],
                "weaponCaliber": [],
                "weaponModsExclusive": [],
                "weaponModsInclusive": []
              },
              {
                "id": "69489225fbb358f1f19a56c6",
                "dynamicLocale": false,
                "target": [
                  "Sandbox",
                  "Sandbox_high"
                ],
                "conditionType": "Location"
              }
            ]
          },
          "conditionType": "CounterCreator"
        },
        {
          "id": "6948931f6d248943789a56d3",
          "index": 3,
          "dynamicLocale": false,
          "visibilityConditions": [],
          "globalQuestCounterId": "",
          "parentId": "",
          "value": 10,
          "type": "Elimination",
          "oneSessionOnly": false,
          "completeInSeconds": 0,
          "doNotResetIfCounterCompleted": false,
          "isResetOnConditionFailed": false,
          "isNecessary": false,
          "counter": {
            "id": "6948931db7ec9e81c09a56d2",
            "conditions": [
              {
                "id": "694893153ead9824d09a56d1",
                "dynamicLocale": false,
                "target": "AnyPmc",
                "value": 1,
                "compareMethod": ">=",
                "conditionType": "Kills",
                "weapon": [
                ],
                "bodyPart": [
                  "Head"
                ],
                "daytime": {
                  "from": 0,
                  "to": 0
                },
                "distance": {
                  "compareMethod": ">=",
                  "value": 0
                },
                "resetOnSessionEnd": false,
                "savageRole": [
                ],
                "enemyEquipmentExclusive": [],
                "enemyEquipmentInclusive": [],
                "enemyHealthEffects": [],
                "weaponCaliber": [],
                "weaponModsExclusive": [],
                "weaponModsInclusive": []
              },
              {
                "id": "694892f96c0d8da6239a56ce",
                "dynamicLocale": false,
                "target": [
                  "TarkovStreets"
                ],
                "conditionType": "Location"
              }
            ]
          },
          "conditionType": "CounterCreator"
        },
        {
          "id": "6948933406f8f12ec19a56d7",
          "index": 4,
          "dynamicLocale": false,
          "visibilityConditions": [],
          "globalQuestCounterId": "",
          "parentId": "",
          "value": 10,
          "type": "Elimination",
          "oneSessionOnly": false,
          "completeInSeconds": 0,
          "doNotResetIfCounterCompleted": false,
          "isResetOnConditionFailed": false,
          "isNecessary": false,
          "counter": {
            "id": "6948933232142d30449a56d6",
            "conditions": [
              {
                "id": "694893313763a21dc19a56d5",
                "dynamicLocale": false,
                "target": "AnyPmc",
                "value": 1,
                "compareMethod": ">=",
                "conditionType": "Kills",
                "weapon": [
                ],
                "bodyPart": [
                  "Head"
                ],
                "daytime": {
                  "from": 0,
                  "to": 0
                },
                "distance": {
                  "compareMethod": ">=",
                  "value": 0
                },
                "resetOnSessionEnd": false,
                "savageRole": [
                ],
                "enemyEquipmentExclusive": [],
                "enemyEquipmentInclusive": [],
                "enemyHealthEffects": [],
                "weaponCaliber": [],
                "weaponModsExclusive": [],
                "weaponModsInclusive": []
              },
              {
                "id": "6948932f00dea0231e9a56d4",
                "dynamicLocale": false,
                "target": [
                  "laboratory"
                ],
                "conditionType": "Location"
              }
            ]
          },
          "conditionType": "CounterCreator"
        },
        {
          "id": "6948935ca05ba888d29a56db",
          "index": 5,
          "dynamicLocale": false,
          "visibilityConditions": [],
          "globalQuestCounterId": "",
          "parentId": "",
          "value": 10,
          "type": "Elimination",
          "oneSessionOnly": false,
          "completeInSeconds": 0,
          "doNotResetIfCounterCompleted": false,
          "isResetOnConditionFailed": false,
          "isNecessary": false,
          "counter": {
            "id": "6948935aaaaf006ad09a56da",
            "conditions": [
              {
                "id": "69489359e2bb2706829a56d9",
                "dynamicLocale": false,
                "target": "AnyPmc",
                "value": 1,
                "compareMethod": ">=",
                "conditionType": "Kills",
                "weapon": [
                ],
                "bodyPart": [
                  "Head"
                ],
                "daytime": {
                  "from": 0,
                  "to": 0
                },
                "distance": {
                  "compareMethod": ">=",
                  "value": 0
                },
                "resetOnSessionEnd": false,
                "savageRole": [
                ],
                "enemyEquipmentExclusive": [],
                "enemyEquipmentInclusive": [],
                "enemyHealthEffects": [],
                "weaponCaliber": [],
                "weaponModsExclusive": [],
                "weaponModsInclusive": []
              },
              {
                "id": "6948936268651c790c9a56dc",
                "dynamicLocale": false,
                "target": [
                  "Woods"
                ],
                "conditionType": "Location"
              }
            ]
          },
          "conditionType": "CounterCreator"
        },
        {
          "id": "69489379fade9f901f9a56e0",
          "index": 6,
          "dynamicLocale": false,
          "visibilityConditions": [],
          "globalQuestCounterId": "",
          "parentId": "",
          "value": 10,
          "type": "Elimination",
          "oneSessionOnly": false,
          "completeInSeconds": 0,
          "doNotResetIfCounterCompleted": false,
          "isResetOnConditionFailed": false,
          "isNecessary": false,
          "counter": {
            "id": "6948937526c206f0a19a56df",
            "conditions": [
              {
                "id": "694893747481f286fd9a56de",
                "dynamicLocale": false,
                "target": "AnyPmc",
                "value": 1,
                "compareMethod": ">=",
                "conditionType": "Kills",
                "weapon": [
                ],
                "bodyPart": [
                  "Head"
                ],
                "daytime": {
                  "from": 0,
                  "to": 0
                },
                "distance": {
                  "compareMethod": ">=",
                  "value": 0
                },
                "resetOnSessionEnd": false,
                "savageRole": [
                ],
                "enemyEquipmentExclusive": [],
                "enemyEquipmentInclusive": [],
                "enemyHealthEffects": [],
                "weaponCaliber": [],
                "weaponModsExclusive": [],
                "weaponModsInclusive": []
              },
              {
                "id": "694893714f29440e3d9a56dd",
                "dynamicLocale": false,
                "target": [
                  "Lighthouse"
                ],
                "conditionType": "Location"
              }
            ]
          },
          "conditionType": "CounterCreator"
        },
        {
          "id": "694893b1dd5f6b36669a56e4",
          "index": 7,
          "dynamicLocale": false,
          "visibilityConditions": [],
          "globalQuestCounterId": "",
          "parentId": "",
          "value": 10,
          "type": "Elimination",
          "oneSessionOnly": false,
          "completeInSeconds": 0,
          "doNotResetIfCounterCompleted": false,
          "isResetOnConditionFailed": false,
          "isNecessary": false,
          "counter": {
            "id": "694893a05657cec26e9a56e3",
            "conditions": [
              {
                "id": "6948939f136825fc8d9a56e2",
                "dynamicLocale": false,
                "target": "AnyPmc",
                "value": 1,
                "compareMethod": ">=",
                "conditionType": "Kills",
                "weapon": [
                ],
                "bodyPart": [
                  "Head"
                ],
                "daytime": {
                  "from": 0,
                  "to": 0
                },
                "distance": {
                  "compareMethod": ">=",
                  "value": 0
                },
                "resetOnSessionEnd": false,
                "savageRole": [
                ],
                "enemyEquipmentExclusive": [],
                "enemyEquipmentInclusive": [],
                "enemyHealthEffects": [],
                "weaponCaliber": [],
                "weaponModsExclusive": [],
                "weaponModsInclusive": []
              },
              {
                "id": "6948939c700fcf7cec9a56e1",
                "dynamicLocale": false,
                "target": [
                  "RezervBase"
                ],
                "conditionType": "Location"
              }
            ]
          },
          "conditionType": "CounterCreator"
        },
        {
          "id": "694893cce6ed18f3c49a56e8",
          "index": 8,
          "dynamicLocale": false,
          "visibilityConditions": [],
          "globalQuestCounterId": "",
          "parentId": "",
          "value": 10,
          "type": "Elimination",
          "oneSessionOnly": false,
          "completeInSeconds": 0,
          "doNotResetIfCounterCompleted": false,
          "isResetOnConditionFailed": false,
          "isNecessary": false,
          "counter": {
            "id": "694893ca2165dac94a9a56e7",
            "conditions": [
              {
                "id": "694893c808b1d25a759a56e6",
                "dynamicLocale": false,
                "target": "AnyPmc",
                "value": 1,
                "compareMethod": ">=",
                "conditionType": "Kills",
                "weapon": [
                ],
                "bodyPart": [
                  "Head"
                ],
                "daytime": {
                  "from": 0,
                  "to": 0
                },
                "distance": {
                  "compareMethod": ">=",
                  "value": 0
                },
                "resetOnSessionEnd": false,
                "savageRole": [
                ],
                "enemyEquipmentExclusive": [],
                "enemyEquipmentInclusive": [],
                "enemyHealthEffects": [],
                "weaponCaliber": [],
                "weaponModsExclusive": [],
                "weaponModsInclusive": []
              },
              {
                "id": "694893c6a0154ec2a09a56e5",
                "dynamicLocale": false,
                "target": [
                  "Shoreline"
                ],
                "conditionType": "Location"
              }
            ]
          },
          "conditionType": "CounterCreator"
        },
        {
          "id": "694893e1b846e397199a56ec",
          "index": 9,
          "dynamicLocale": false,
          "visibilityConditions": [],
          "globalQuestCounterId": "",
          "parentId": "",
          "value": 10,
          "type": "Elimination",
          "oneSessionOnly": false,
          "completeInSeconds": 0,
          "doNotResetIfCounterCompleted": false,
          "isResetOnConditionFailed": false,
          "isNecessary": false,
          "counter": {
            "id": "694893dfb3160e56379a56eb",
            "conditions": [
              {
                "id": "694893ded1b0b259b29a56ea",
                "dynamicLocale": false,
                "target": "AnyPmc",
                "value": 1,
                "compareMethod": ">=",
                "conditionType": "Kills",
                "weapon": [
                ],
                "bodyPart": [
                  "Head"
                ],
                "daytime": {
                  "from": 0,
                  "to": 0
                },
                "distance": {
                  "compareMethod": ">=",
                  "value": 0
                },
                "resetOnSessionEnd": false,
                "savageRole": [
                ],
                "enemyEquipmentExclusive": [],
                "enemyEquipmentInclusive": [],
                "enemyHealthEffects": [],
                "weaponCaliber": [],
                "weaponModsExclusive": [],
                "weaponModsInclusive": []
              },
              {
                "id": "694893db8b842872d79a56e9",
                "dynamicLocale": false,
                "target": [
                  "Interchange"
                ],
                "conditionType": "Location"
              }
            ]
          },
          "conditionType": "CounterCreator"
        }
      ],
      "fail": []
    },
    "instantComplete": false,
    "showNotificationsInGame": false,
    "showProgress": false,
    "prefab": "",
    "rarity": "Rare",
    "hidden": false,
    "showConditions": true,
    "progressBarEnabled": true,
    "side": "Pmc",
    "index": 9001
  },
  {
    "id": "69488ddbe04d15d5539a56b1",
    "imageUrl": "/files/achievement/killatargeticon.png",
    "assetPath": "",
    "rewards": [
      {
        "id": "69488ddc97118b09d89a56b2",
        "unknown": false,
        "gameMode": [],
        "availableInGameEditions": [],
        "illustrationConfig": null,
        "isHidden": false,
        "target": "68f1500a8e0bff44ce023f1e",
        "type": "CustomizationDirect"
      }
    ],
    "conditions": {
      "availableForFinish": [
        {
          "id": "69488def123508d2b59a56b3",
          "index": 0,
          "dynamicLocale": false,
          "visibilityConditions": [],
          "globalQuestCounterId": "",
          "parentId": "",
          "value": 5,
          "type": "Elimination",
          "oneSessionOnly": false,
          "completeInSeconds": 0,
          "doNotResetIfCounterCompleted": false,
          "isResetOnConditionFailed": false,
          "isNecessary": false,
          "counter": {
            "id": "69488df4b931f0b80c9a56b4",
            "conditions": [
              {
                "id": "69488df619293f065e9a56b5",
                "dynamicLocale": false,
                "target": "Savage",
                "value": 1,
                "compareMethod": ">=",
                "conditionType": "Kills",
                "weapon": [
                ],
                "bodyPart": [
                  "LeftLeg",
                  "RightLeg"
                ],
                "daytime": {
                  "from": 0,
                  "to": 0
                },
                "distance": {
                  "compareMethod": ">=",
                  "value": 0
                },
                "resetOnSessionEnd": false,
                "savageRole": [
                  "bossKilla"
                ],
                "enemyEquipmentExclusive": [],
                "enemyEquipmentInclusive": [],
                "enemyHealthEffects": [],
                "weaponCaliber": [],
                "weaponModsExclusive": [],
                "weaponModsInclusive": []
              }
            ]
          },
          "conditionType": "CounterCreator"
        }
      ],
      "fail": []
    },
    "instantComplete": false,
    "showNotificationsInGame": false,
    "showProgress": false,
    "prefab": "",
    "rarity": "Rare",
    "hidden": false,
    "showConditions": false,
    "progressBarEnabled": true,
    "side": "Pmc",
    "index": 9001
  },
  {
    "id": "69485d4228fbbf7227ff89c1",
    "imageUrl": "/files/achievement/knighttargeticon.png",
    "assetPath": "",
    "rewards": [
      {
        "id": "69485d43ef6d69b8f2ff89c2",
        "unknown": false,
        "gameMode": [],
        "availableInGameEditions": [],
        "illustrationConfig": null,
        "isHidden": false,
        "target": "68f151bf79e73568c40a7938",
        "type": "CustomizationDirect"
      }
    ],
    "conditions": {
      "availableForFinish": [
        {
          "id": "69485d491300b85773ff89c3",
          "index": 0,
          "dynamicLocale": false,
          "visibilityConditions": [],
          "globalQuestCounterId": "",
          "parentId": "",
          "value": 1,
          "type": "Elimination",
          "oneSessionOnly": false,
          "completeInSeconds": 0,
          "doNotResetIfCounterCompleted": false,
          "isResetOnConditionFailed": false,
          "isNecessary": false,
          "counter": {
            "id": "69485d4b90c2d0f0fbff89c4",
            "conditions": [
              {
                "id": "69485d4cf3e51d0528ff89c5",
                "dynamicLocale": false,
                "target": "Savage",
                "value": 1,
                "compareMethod": ">=",
                "conditionType": "Kills",
                "weapon": [
                ],
                "bodyPart": [
                  "Head"
                ],
                "daytime": {
                  "from": 0,
                  "to": 0
                },
                "distance": {
                  "compareMethod": ">=",
                  "value": 0
                },
                "resetOnSessionEnd": false,
                "savageRole": [
                  "bossKnight"
                ],
                "enemyEquipmentExclusive": [],
                "enemyEquipmentInclusive": [],
                "enemyHealthEffects": [],
                "weaponCaliber": [],
                "weaponModsExclusive": [],
                "weaponModsInclusive": []
              },
              {
                "id": "69485e0b98efdf4f8dff89c6",
                "dynamicLocale": false,
                "target": [
                  "bigmap"
                ],
                "conditionType": "Location"
              }
            ]
          },
          "conditionType": "CounterCreator"
        },
        {
          "id": "69485e1d811f8e1e9eff89c7",
          "index": 1,
          "dynamicLocale": false,
          "visibilityConditions": [],
          "globalQuestCounterId": "",
          "parentId": "",
          "value": 1,
          "type": "Elimination",
          "oneSessionOnly": false,
          "completeInSeconds": 0,
          "doNotResetIfCounterCompleted": false,
          "isResetOnConditionFailed": false,
          "isNecessary": false,
          "counter": {
            "id": "69485e20101febac97ff89c8",
            "conditions": [
              {
                "id": "69485e21d76a48dfe6ff89c9",
                "dynamicLocale": false,
                "target": "Savage",
                "value": 1,
                "compareMethod": ">=",
                "conditionType": "Kills",
                "weapon": [
                ],
                "bodyPart": [
                  "Head"
                ],
                "daytime": {
                  "from": 0,
                  "to": 0
                },
                "distance": {
                  "compareMethod": ">=",
                  "value": 0
                },
                "resetOnSessionEnd": false,
                "savageRole": [
                  "bossKnight"
                ],
                "enemyEquipmentExclusive": [],
                "enemyEquipmentInclusive": [],
                "enemyHealthEffects": [],
                "weaponCaliber": [],
                "weaponModsExclusive": [],
                "weaponModsInclusive": []
              },
              {
                "id": "69485e247a3d58426eff89ca",
                "dynamicLocale": false,
                "target": [
                  "Woods"
                ],
                "conditionType": "Location"
              }
            ]
          },
          "conditionType": "CounterCreator"
        },
        {
          "id": "69485e59b66152e3e0ff89ce",
          "index": 2,
          "dynamicLocale": false,
          "visibilityConditions": [],
          "globalQuestCounterId": "",
          "parentId": "",
          "value": 1,
          "type": "Elimination",
          "oneSessionOnly": false,
          "completeInSeconds": 0,
          "doNotResetIfCounterCompleted": false,
          "isResetOnConditionFailed": false,
          "isNecessary": false,
          "counter": {
            "id": "69485e58b69f243a3fff89cd",
            "conditions": [
              {
                "id": "69485e570cd3a1d145ff89cc",
                "dynamicLocale": false,
                "target": "Savage",
                "value": 1,
                "compareMethod": ">=",
                "conditionType": "Kills",
                "weapon": [
                ],
                "bodyPart": [
                  "Head"
                ],
                "daytime": {
                  "from": 0,
                  "to": 0
                },
                "distance": {
                  "compareMethod": ">=",
                  "value": 0
                },
                "resetOnSessionEnd": false,
                "savageRole": [
                  "bossKnight"
                ],
                "enemyEquipmentExclusive": [],
                "enemyEquipmentInclusive": [],
                "enemyHealthEffects": [],
                "weaponCaliber": [],
                "weaponModsExclusive": [],
                "weaponModsInclusive": []
              },
              {
                "id": "69485e54b1ade22bf7ff89cb",
                "dynamicLocale": false,
                "target": [
                  "Shoreline"
                ],
                "conditionType": "Location"
              }
            ]
          },
          "conditionType": "CounterCreator"
        },
        {
          "id": "69485ea2860fa0532aff89d6",
          "index": 3,
          "dynamicLocale": false,
          "visibilityConditions": [],
          "globalQuestCounterId": "",
          "parentId": "",
          "value": 1,
          "type": "Elimination",
          "oneSessionOnly": false,
          "completeInSeconds": 0,
          "doNotResetIfCounterCompleted": false,
          "isResetOnConditionFailed": false,
          "isNecessary": false,
          "counter": {
            "id": "69485ea095dba495d0ff89d5",
            "conditions": [
              {
                "id": "69485e9eb75368cb02ff89d4",
                "dynamicLocale": false,
                "target": "Savage",
                "value": 1,
                "compareMethod": ">=",
                "conditionType": "Kills",
                "weapon": [
                ],
                "bodyPart": [
                  "Head"
                ],
                "daytime": {
                  "from": 0,
                  "to": 0
                },
                "distance": {
                  "compareMethod": ">=",
                  "value": 0
                },
                "resetOnSessionEnd": false,
                "savageRole": [
                  "bossKnight"
                ],
                "enemyEquipmentExclusive": [],
                "enemyEquipmentInclusive": [],
                "enemyHealthEffects": [],
                "weaponCaliber": [],
                "weaponModsExclusive": [],
                "weaponModsInclusive": []
              },
              {
                "id": "69485e9c47879d69a8ff89d3",
                "dynamicLocale": false,
                "target": [
                  "Lighthouse"
                ],
                "conditionType": "Location"
              }
            ]
          },
          "conditionType": "CounterCreator"
        }
      ],
      "fail": []
    },
    "instantComplete": false,
    "showNotificationsInGame": false,
    "showProgress": false,
    "prefab": "",
    "rarity": "Rare",
    "hidden": false,
    "showConditions": true,
    "progressBarEnabled": true,
    "side": "Pmc",
    "index": 9001
  },
  {
    "id": "694735758b9b166676ff89b6",
    "imageUrl": "/files/achievement/zryachiytargeticon.png",
    "assetPath": "",
    "rewards": [
      {
        "id": "69473576ac3245991aff89b7",
        "unknown": false,
        "gameMode": [],
        "availableInGameEditions": [],
        "illustrationConfig": null,
        "isHidden": false,
        "target": "68f1516fd4bee20384008afa",
        "type": "CustomizationDirect"
      }
    ],
    "conditions": {
      "availableForFinish": [
        {
          "id": "6947357a7f0b458a0aff89b8",
          "index": 0,
          "dynamicLocale": false,
          "visibilityConditions": [],
          "globalQuestCounterId": "",
          "parentId": "",
          "value": 3,
          "type": "Elimination",
          "oneSessionOnly": false,
          "completeInSeconds": 0,
          "doNotResetIfCounterCompleted": false,
          "isResetOnConditionFailed": false,
          "isNecessary": false,
          "counter": {
            "id": "69473584c92a25525aff89b9",
            "conditions": [
              {
                "id": "69473586e5b3480be4ff89ba",
                "dynamicLocale": false,
                "target": "Any",
                "value": 1,
                "compareMethod": ">=",
                "conditionType": "Kills",
                "weapon": [
                ],
                "bodyPart": [
                  "Head"
                ],
                "daytime": {
                  "from": 0,
                  "to": 0
                },
                "distance": {
                  "compareMethod": ">=",
                  "value": 350
                },
                "resetOnSessionEnd": false,
                "savageRole": [
                ],
                "enemyEquipmentExclusive": [],
                "enemyEquipmentInclusive": [],
                "enemyHealthEffects": [],
                "weaponCaliber": [],
                "weaponModsExclusive": [],
                "weaponModsInclusive": []
              }
            ]
          },
          "conditionType": "CounterCreator"
        }
      ],
      "fail": []
    },
    "instantComplete": false,
    "showNotificationsInGame": false,
    "showProgress": false,
    "prefab": "",
    "rarity": "Rare",
    "hidden": false,
    "showConditions": false,
    "progressBarEnabled": true,
    "side": "Pmc",
    "index": 9001
  },
  {
    "id": "69485047a741eee797ff89bb",
    "imageUrl": "/files/achievement/cockereltargeticon.png",
    "assetPath": "",
    "rewards": [
      {
        "id": "69485a12674b2456b1ff89bc",
        "unknown": false,
        "gameMode": [],
        "availableInGameEditions": [],
        "illustrationConfig": null,
        "isHidden": false,
        "target": "68f11506a1e799f1c3027c79",
        "type": "CustomizationDirect"
      }
    ],
    "conditions": {
      "availableForFinish": [
        {
          "id": "69485a210642641711ff89bd",
          "index": 0,
          "dynamicLocale": false,
          "visibilityConditions": [],
          "globalQuestCounterId": "",
          "parentId": "",
          "value": 11,
          "type": "Elimination",
          "oneSessionOnly": true,
          "completeInSeconds": 0,
          "doNotResetIfCounterCompleted": false,
          "isResetOnConditionFailed": false,
          "isNecessary": false,
          "counter": {
            "id": "69485a225eb892b0f1ff89be",
            "conditions": [
              {
                "id": "69485a246b11b539a0ff89bf",
                "dynamicLocale": false,
                "target": "Savage",
                "value": 1,
                "compareMethod": ">=",
                "conditionType": "Kills",
                "weapon": [
                ],
                "bodyPart": [
                  "Head"
                ],
                "daytime": {
                  "from": 6,
                  "to": 11
                },
                "distance": {
                  "compareMethod": ">=",
                  "value": 0
                },
                "resetOnSessionEnd": false,
                "savageRole": [
                  "assault",
                  "marksman"
                ],
                "enemyEquipmentExclusive": [],
                "enemyEquipmentInclusive": [],
                "enemyHealthEffects": [],
                "weaponCaliber": [],
                "weaponModsExclusive": [],
                "weaponModsInclusive": []
              }
            ]
          },
          "conditionType": "CounterCreator"
        }
      ],
      "fail": []
    },
    "instantComplete": false,
    "showNotificationsInGame": false,
    "showProgress": false,
    "prefab": "",
    "rarity": "Rare",
    "hidden": false,
    "showConditions": false,
    "progressBarEnabled": true,
    "side": "Pmc",
    "index": 9001
  },
  {
    "id": "6945fed89b863ef9ce9f67ce",
    "imageUrl": "/files/achievement/axemantargeticon.png",
    "assetPath": "",
    "rewards": [
      {
        "id": "694614f8fd79c4c9279f67d9",
        "unknown": false,
        "gameMode": [],
        "availableInGameEditions": [],
        "illustrationConfig": null,
        "isHidden": false,
        "target": "68f6159355deae75be0f3bb6",
        "type": "CustomizationDirect"
      }
    ],
    "conditions": {
      "availableForFinish": [
        {
          "id": "6945fedac9817e95ab9f67cf",
          "index": 0,
          "dynamicLocale": false,
          "visibilityConditions": [],
          "globalQuestCounterId": "",
          "parentId": "",
          "value": 3,
          "type": "Elimination",
          "oneSessionOnly": true,
          "completeInSeconds": 0,
          "doNotResetIfCounterCompleted": false,
          "isResetOnConditionFailed": false,
          "isNecessary": false,
          "counter": {
            "id": "6945fedce960d3a6999f67d0",
            "conditions": [
              {
                "id": "6945fedeb6943e05e09f67d1",
                "dynamicLocale": false,
                "target": "Any",
                "value": 1,
                "compareMethod": ">=",
                "conditionType": "Kills",
                "weapon": [
                  "57cd379a24597778e7682ecf"
                ],
                "bodyPart": [
                ],
                "daytime": {
                  "from": 0,
                  "to": 0
                },
                "distance": {
                  "compareMethod": ">=",
                  "value": 0
                },
                "resetOnSessionEnd": false,
                "savageRole": [
                ],
                "enemyEquipmentExclusive": [],
                "enemyEquipmentInclusive": [],
                "enemyHealthEffects": [],
                "weaponCaliber": [],
                "weaponModsExclusive": [],
                "weaponModsInclusive": []
              }
            ]
          },
          "conditionType": "CounterCreator"
        }
      ],
      "fail": []
    },
    "instantComplete": false,
    "showNotificationsInGame": false,
    "showProgress": false,
    "prefab": "",
    "rarity": "Rare",
    "hidden": false,
    "showConditions": false,
    "progressBarEnabled": true,
    "side": "Pmc",
    "index": 9001
  },
  {
    "id": "69460c424c23a6e66f9f67d3",
    "imageUrl": "/files/achievement/aceofspadestargeticon.png",
    "assetPath": "",
    "rewards": [
      {
        "id": "6946162669e6b2b4179f67db",
        "unknown": false,
        "gameMode": [],
        "availableInGameEditions": [],
        "illustrationConfig": null,
        "isHidden": false,
        "target": "68f615b0c7592f88510b1c32",
        "type": "CustomizationDirect"
      }
    ],
    "conditions": {
      "availableForFinish": [
        {
          "id": "69460c449235467ed99f67d4",
          "index": 0,
          "dynamicLocale": false,
          "visibilityConditions": [],
          "globalQuestCounterId": "",
          "parentId": "",
          "value": 8,
          "type": "Elimination",
          "oneSessionOnly": false,
          "completeInSeconds": 0,
          "doNotResetIfCounterCompleted": false,
          "isResetOnConditionFailed": false,
          "isNecessary": false,
          "counter": {
            "id": "69460c450b0c0d55179f67d5",
            "conditions": [
              {
                "id": "69460c460e686ab6f69f67d6",
                "dynamicLocale": false,
                "target": "AnyPmc",
                "value": 1,
                "compareMethod": ">=",
                "conditionType": "Kills",
                "weapon": [
                  "61a4c8884f95bc3b2c5dc96f",
                  "624c2e8614da335f1e034d8c",
                  "633ec7c2a6918cb895019c6c"
                ],
                "bodyPart": [
                  "Head"
                ],
                "daytime": {
                  "from": 0,
                  "to": 0
                },
                "distance": {
                  "compareMethod": ">=",
                  "value": 0
                },
                "resetOnSessionEnd": false,
                "savageRole": [
                ],
                "enemyEquipmentExclusive": [],
                "enemyEquipmentInclusive": [],
                "enemyHealthEffects": [],
                "weaponCaliber": [],
                "weaponModsExclusive": [],
                "weaponModsInclusive": []
              }
            ]
          },
          "conditionType": "CounterCreator"
        }
      ],
      "fail": []
    },
    "instantComplete": false,
    "showNotificationsInGame": false,
    "showProgress": false,
    "prefab": "",
    "rarity": "Rare",
    "hidden": false,
    "showConditions": false,
    "progressBarEnabled": true,
    "side": "Pmc",
    "index": 9001
  }
]  